{
 "cells": [
  {
   "cell_type": "code",
   "execution_count": 1,
   "metadata": {},
   "outputs": [],
   "source": [
    "nums = list(range(10_000))\n",
    "# or you can use the range directly with\n",
    "nums = range(10_000)"
   ]
  },
  {
   "cell_type": "code",
   "execution_count": 2,
   "metadata": {},
   "outputs": [],
   "source": [
    "def for_loop():\n",
    "    doubles = []\n",
    "    for num in nums:\n",
    "        doubles.append(num*2)"
   ]
  },
  {
   "cell_type": "code",
   "execution_count": 3,
   "metadata": {},
   "outputs": [
    {
     "name": "stdout",
     "output_type": "stream",
     "text": [
      "437 µs ± 3.12 µs per loop (mean ± std. dev. of 7 runs, 1,000 loops each)\n"
     ]
    }
   ],
   "source": [
    "%timeit for_loop()"
   ]
  },
  {
   "cell_type": "code",
   "execution_count": 4,
   "metadata": {},
   "outputs": [],
   "source": [
    "def list_comprehension():\n",
    "    doubles = [num*2 for num in nums]"
   ]
  },
  {
   "cell_type": "code",
   "execution_count": 5,
   "metadata": {},
   "outputs": [
    {
     "name": "stdout",
     "output_type": "stream",
     "text": [
      "335 µs ± 708 ns per loop (mean ± std. dev. of 7 runs, 1,000 loops each)\n"
     ]
    }
   ],
   "source": [
    "%timeit list_comprehension()"
   ]
  },
  {
   "cell_type": "code",
   "execution_count": 6,
   "metadata": {},
   "outputs": [
    {
     "name": "stdout",
     "output_type": "stream",
     "text": [
      "30.45%\n"
     ]
    }
   ],
   "source": [
    "print(f'{((437 / 335) - 1) * 100:.2f}%')"
   ]
  },
  {
   "cell_type": "code",
   "execution_count": 7,
   "metadata": {},
   "outputs": [],
   "source": [
    "import dis"
   ]
  },
  {
   "cell_type": "code",
   "execution_count": 8,
   "metadata": {},
   "outputs": [
    {
     "name": "stdout",
     "output_type": "stream",
     "text": [
      "  1           0 RESUME                   0\n",
      "\n",
      "  2           2 BUILD_LIST               0\n",
      "              4 STORE_FAST               0 (doubles)\n",
      "\n",
      "  3           6 LOAD_GLOBAL              0 (nums)\n",
      "             18 GET_ITER\n",
      "        >>   20 FOR_ITER                26 (to 74)\n",
      "             22 STORE_FAST               1 (num)\n",
      "\n",
      "  4          24 LOAD_FAST                0 (doubles)\n",
      "             26 LOAD_METHOD              1 (append)\n",
      "             48 LOAD_FAST                1 (num)\n",
      "             50 LOAD_CONST               1 (2)\n",
      "             52 BINARY_OP                5 (*)\n",
      "             56 PRECALL                  1\n",
      "             60 CALL                     1\n",
      "             70 POP_TOP\n",
      "             72 JUMP_BACKWARD           27 (to 20)\n",
      "\n",
      "  3     >>   74 LOAD_CONST               0 (None)\n",
      "             76 RETURN_VALUE\n"
     ]
    }
   ],
   "source": [
    "dis.dis(for_loop)"
   ]
  },
  {
   "cell_type": "code",
   "execution_count": 9,
   "metadata": {},
   "outputs": [
    {
     "name": "stdout",
     "output_type": "stream",
     "text": [
      "  1           0 RESUME                   0\n",
      "\n",
      "  2           2 LOAD_CONST               1 (<code object <listcomp> at 0x0000027612379480, file \"C:\\Users\\dboct\\AppData\\Local\\Temp\\ipykernel_15448\\176160246.py\", line 2>)\n",
      "              4 MAKE_FUNCTION            0\n",
      "              6 LOAD_GLOBAL              0 (nums)\n",
      "             18 GET_ITER\n",
      "             20 PRECALL                  0\n",
      "             24 CALL                     0\n",
      "             34 STORE_FAST               0 (doubles)\n",
      "             36 LOAD_CONST               0 (None)\n",
      "             38 RETURN_VALUE\n",
      "\n",
      "Disassembly of <code object <listcomp> at 0x0000027612379480, file \"C:\\Users\\dboct\\AppData\\Local\\Temp\\ipykernel_15448\\176160246.py\", line 2>:\n",
      "  2           0 RESUME                   0\n",
      "              2 BUILD_LIST               0\n",
      "              4 LOAD_FAST                0 (.0)\n",
      "        >>    6 FOR_ITER                 7 (to 22)\n",
      "              8 STORE_FAST               1 (num)\n",
      "             10 LOAD_FAST                1 (num)\n",
      "             12 LOAD_CONST               0 (2)\n",
      "             14 BINARY_OP                5 (*)\n",
      "             18 LIST_APPEND              2\n",
      "             20 JUMP_BACKWARD            8 (to 6)\n",
      "        >>   22 RETURN_VALUE\n"
     ]
    }
   ],
   "source": [
    "dis.dis(list_comprehension)"
   ]
  },
  {
   "cell_type": "markdown",
   "metadata": {},
   "source": [
    "# Map"
   ]
  },
  {
   "cell_type": "code",
   "execution_count": 10,
   "metadata": {},
   "outputs": [],
   "source": [
    "def double(num):\n",
    "    return num * 2\n",
    "\n",
    "def map_func():\n",
    "    doubles = list(map(double, nums))"
   ]
  },
  {
   "cell_type": "code",
   "execution_count": 11,
   "metadata": {},
   "outputs": [
    {
     "name": "stdout",
     "output_type": "stream",
     "text": [
      "664 µs ± 3.83 µs per loop (mean ± std. dev. of 7 runs, 1,000 loops each)\n"
     ]
    }
   ],
   "source": [
    "%timeit map_func()"
   ]
  },
  {
   "cell_type": "code",
   "execution_count": 12,
   "metadata": {},
   "outputs": [],
   "source": [
    "words = ['str'] * 10_000"
   ]
  },
  {
   "cell_type": "code",
   "execution_count": 13,
   "metadata": {},
   "outputs": [
    {
     "name": "stdout",
     "output_type": "stream",
     "text": [
      "515 µs ± 10.6 µs per loop (mean ± std. dev. of 7 runs, 1,000 loops each)\n"
     ]
    }
   ],
   "source": [
    "def for_loop_upper():\n",
    "    upper = []\n",
    "    for word in words:\n",
    "        upper.append(word.upper())\n",
    "        \n",
    "%timeit for_loop_upper()"
   ]
  },
  {
   "cell_type": "code",
   "execution_count": 14,
   "metadata": {},
   "outputs": [
    {
     "name": "stdout",
     "output_type": "stream",
     "text": [
      "374 µs ± 1.45 µs per loop (mean ± std. dev. of 7 runs, 1,000 loops each)\n"
     ]
    }
   ],
   "source": [
    "def list_comprehension_upper():\n",
    "    upper = [word.upper() for word in words]\n",
    "\n",
    "%timeit list_comprehension_upper()"
   ]
  },
  {
   "cell_type": "code",
   "execution_count": 15,
   "metadata": {},
   "outputs": [
    {
     "name": "stdout",
     "output_type": "stream",
     "text": [
      "306 µs ± 893 ns per loop (mean ± std. dev. of 7 runs, 1,000 loops each)\n"
     ]
    }
   ],
   "source": [
    "def map_upper():\n",
    "    upper = list(map(str.upper, words))\n",
    "\n",
    "%timeit map_upper()"
   ]
  },
  {
   "cell_type": "markdown",
   "metadata": {},
   "source": [
    "## Appendix"
   ]
  },
  {
   "cell_type": "code",
   "execution_count": 16,
   "metadata": {},
   "outputs": [],
   "source": [
    "def hello(): print('Hello, World!')"
   ]
  },
  {
   "cell_type": "code",
   "execution_count": 17,
   "metadata": {},
   "outputs": [
    {
     "name": "stdout",
     "output_type": "stream",
     "text": [
      "  1           0 RESUME                   0\n",
      "              2 LOAD_GLOBAL              1 (NULL + print)\n",
      "             14 LOAD_CONST               1 ('Hello, World!')\n",
      "             16 PRECALL                  1\n",
      "             20 CALL                     1\n",
      "             30 POP_TOP\n",
      "             32 LOAD_CONST               0 (None)\n",
      "             34 RETURN_VALUE\n"
     ]
    }
   ],
   "source": [
    "dis.dis(hello)"
   ]
  }
 ],
 "metadata": {
  "kernelspec": {
   "display_name": "Python 3",
   "language": "python",
   "name": "python3"
  },
  "language_info": {
   "codemirror_mode": {
    "name": "ipython",
    "version": 3
   },
   "file_extension": ".py",
   "mimetype": "text/x-python",
   "name": "python",
   "nbconvert_exporter": "python",
   "pygments_lexer": "ipython3",
   "version": "3.11.5"
  },
  "orig_nbformat": 4
 },
 "nbformat": 4,
 "nbformat_minor": 2
}
